[
    {
        "title" : "Cracking the coding interview",
        "img" : "https://res.cloudinary.com/thecodergeek/image/upload/v1631889117/cracking-sde_zf2q3s.jpg",
        "author" : "Gayle Laakmann McDowell",
        "link" : "https://t.me/interviewpreptech/4"
    },
    {
        "title" : "Data Structures And Algorithms Made Easy",
        "img" : "https://res.cloudinary.com/thecodergeek/image/upload/v1631889303/dsa-made-easy_emel0h.jpg",
        "author" : "Narasimha Karumanchi",
        "link" : "https://t.me/interviewpreptech/10"
    },
    {
        "title" : "Algorithm Notes for Professionals",
        "img" : "https://res.cloudinary.com/thecodergeek/image/upload/v1631889618/Screenshot_20210917-200918_flvt5o.jpg",
        "author" : "Goalkicker",
        "link" : "https://t.me/interviewpreptech/13"
    },
    {
        "title" : "Guide to Competitve Programming",
        "img" : "https://res.cloudinary.com/thecodergeek/image/upload/v1631889705/61eKRhl_NEL_mjhssk.jpg",
        "author" : "Antti Laaksonen",
        "link" : "https://t.me/interviewpreptech/7"
    },
    {
        "title" : "Clean Code",
        "img" : "https://res.cloudinary.com/thecodergeek/image/upload/v1631889897/41yafGMO_rL._SX376_BO1_204_203_200__hhb0c8.jpg",
        "author" : "Martin Robert ",
        "link" : "https://t.me/thecodergeek/110"
    },
    {
        "title" : "97 Things Every Programmer Should Know",
        "img" : "https://res.cloudinary.com/thecodergeek/image/upload/v1631894258/71_p3YjTZ4L_vj6z1b.jpg",
        "author" : "Kevlin Henney",
        "link" : "https://t.me/interviewpreptech/17"
    }
]